calculatecircleareatool/__init__.py
calculatecircleareatool/__main__.py
calculatecircleareatool-0.1.0.dist-info/METADATA
calculatecircleareatool-0.1.0.dist-info/WHEEL
calculatecircleareatool-0.1.0.dist-info/entry_points.txt
calculatecircleareatool-0.1.0.dist-info/top_level.txt
calculatecircleareatool-0.1.0.dist-info/RECORD
