Metadata-Version: 2.4
Name: calculatecircleareatool
Version: 0.1.0
Summary: A tool to calculate area of a circle
Requires-Python: >=3.8
